llm_math_education/__init__.py
llm_math_education/chat_db.py
llm_math_education/embedding_utils.py
llm_math_education/env_utils.py
llm_math_education/gpf_utils.py
llm_math_education/logit_bias.py
llm_math_education/misconceptions.py
llm_math_education/openstax.py
llm_math_education/prompt_utils.py
llm_math_education/prompts/hints.py
llm_math_education/prompts/mathqa.py
llm_math_education/resources/dolma_stopwords.json
llm_math_education/resources/misconceptions.ndjson
llm_math_education/retrieval.py
llm_math_education/retrieval_strategies.py
llm_math_education-0.5.1.dist-info/LICENSE
llm_math_education-0.5.1.dist-info/METADATA
llm_math_education-0.5.1.dist-info/WHEEL
llm_math_education-0.5.1.dist-info/RECORD
