Metadata-Version: 2.1
Name: llm-math-education
Version: 0.5.1
Summary: Retrieval-backed LLMs for math education
Home-page: https://github.com/levon003/llm-math-education.git
License: MIT
Author: Zachary Levonian
Author-email: zach@digitalharbor.org
Requires-Python: >=3.10,<3.13
Classifier: License :: OSI Approved :: MIT License
Classifier: Programming Language :: Python :: 3
Classifier: Programming Language :: Python :: 3.10
Classifier: Programming Language :: Python :: 3.11
Requires-Dist: argon2-cffi (>=21.3.0,<22.0.0)
Requires-Dist: openai (>=0.27.8,<0.28.0)
Requires-Dist: pandas (>=2.0.2,<3.0.0)
Requires-Dist: poetry (==1.4.0)
Requires-Dist: python-dotenv (>=1.0.0,<2.0.0)
Requires-Dist: scipy (>=1.11.0,<2.0.0)
Requires-Dist: streamlit (>=1.23.1,<2.0.0)
Requires-Dist: tiktoken (>=0.4.0,<0.5.0)
Project-URL: Repository, https://github.com/levon003/llm-math-education.git
